tests/__init__.py
tests/test_tasks.py
todo_cli/__init__.py
todo_cli/__main__.py
todo_cli/cli.py
todo_cli/models.py
todo_cli/storage.py
ogc_todo_cli-1.0.3.dist-info/METADATA
ogc_todo_cli-1.0.3.dist-info/WHEEL
ogc_todo_cli-1.0.3.dist-info/entry_points.txt
ogc_todo_cli-1.0.3.dist-info/top_level.txt
ogc_todo_cli-1.0.3.dist-info/RECORD
