Metadata-Version: 2.4
Name: ogc-todo-cli
Version: 1.0.3
Summary: A simple command-line To-Do manager built in Python
Author: Nwaokolo Godstime
Author-email: Nwaokolo Godstime <lionartogc.com@gmail.com>
Requires-Python: >=3.8
